blitzdb/__init__.py
blitzdb/document.py
blitzdb/helpers.py
blitzdb/queryset.py
blitzdb/backends/__init__.py
blitzdb/backends/base.py
blitzdb/backends/file/__init__.py
blitzdb/backends/file/backend.py
blitzdb/backends/file/index.py
blitzdb/backends/file/queries.py
blitzdb/backends/file/queryset.py
blitzdb/backends/file/serializers.py
blitzdb/backends/file/store.py
blitzdb/backends/file/utils.py
blitzdb/backends/mongo/__init__.py
blitzdb/backends/mongo/backend.py
blitzdb/backends/mongo/queryset.py
blitzdb/backends/sql/__init__.py
blitzdb/backends/sql/backend.py
blitzdb/backends/sql/queryset.py
blitzdb/backends/sql/relations.py
blitzdb/fields/__init__.py
blitzdb/fields/base.py
blitzdb/fields/binary.py
blitzdb/fields/boolean.py
blitzdb/fields/char.py
blitzdb/fields/date.py
blitzdb/fields/datetime.py
blitzdb/fields/email.py
blitzdb/fields/enum.py
blitzdb/fields/float.py
blitzdb/fields/foreignkey.py
blitzdb/fields/integer.py
blitzdb/fields/manytomany.py
blitzdb/fields/onetomany.py
blitzdb/fields/text.py
blitzdb3_ce-4.0.9.dist-info/LICENSE.txt
blitzdb3_ce-4.0.9.dist-info/METADATA
blitzdb3_ce-4.0.9.dist-info/WHEEL
blitzdb3_ce-4.0.9.dist-info/top_level.txt
blitzdb3_ce-4.0.9.dist-info/RECORD
