Metadata-Version: 2.1
Name: blitzdb3-ce
Version: 4.0.9
Summary: A document-oriented database written purely in Python.
Home-page: https://github.com/tcosolutions/blitzdb3-ce
License: MIT
Classifier: Intended Audience :: Developers
Classifier: Programming Language :: Python
Classifier: Topic :: Database
License-File: LICENSE.txt
